function_debugger/__init__.py
function_debugger/function_debugger.py
function_debugger-2.0.dist-info/METADATA
function_debugger-2.0.dist-info/WHEEL
function_debugger-2.0.dist-info/top_level.txt
function_debugger-2.0.dist-info/RECORD
