Metadata-Version: 2.4
Name: function_debugger
Version: 2.0
Summary: debugger
Author-email: howShouldIChosseMyUsername <trademark2179@gmail.com>
License: MIT
Requires-Python: >=3.7
